rocktree.py
rocktree_server.py
rocktree-1.0.0.dist-info/WHEEL
rocktree-1.0.0.dist-info/METADATA
rocktree-1.0.0.dist-info/RECORD
