Metadata-Version: 2.1
Name: rocktree
Version: 1.0.0
Summary: Rock Solid Library for syncing progress online with byte to byte same working tree.
Home-page: https://github.com/xcodz-dot/rocktree
License: LGPL-2.1-only
Author: xcodz-dot
Author-email: 71920621+xcodz-dot@users.noreply.github.com
Requires-Python: >=3.7,<4.0
Classifier: License :: OSI Approved
Classifier: Programming Language :: Python :: 3
Classifier: Programming Language :: Python :: 3.10
Classifier: Programming Language :: Python :: 3.7
Classifier: Programming Language :: Python :: 3.8
Classifier: Programming Language :: Python :: 3.9
Provides-Extra: server
Provides-Extra: server-gevent
Requires-Dist: flask (>=2.0.2,<3.0.0); extra == "server" or extra == "server-gevent"
Requires-Dist: gevent (>=21.12.0); extra == "server-gevent"
Requires-Dist: patchutils (>=1.1.3,<2.0.0)
Requires-Dist: requests (>=2.26.0,<3.0.0)
Project-URL: Repository, https://github.com/xcodz-dot/rocktree
